[
  {
    "id": "2c250b7e-bf5a-8003-8524-f05893c8fa7b",
    "name": "Creeper Shoes",
    "description": "Thick-soled creeper shoes.",
    "hasImage": false
  },
  {
    "id": "2c250b7e-bf5a-8003-a624-c951925f8928",
    "name": "Winnerwell Stove",
    "description": "Portable wood stove (camp / cabin).",
    "hasImage": false
  },
  {
    "id": "2c250b7e-bf5a-8004-ba94-dccd03a62da6",
    "name": "New Ski Boots",
    "description": "Replace boots.",
    "hasImage": false
  },
  {
    "id": "2c250b7e-bf5a-8009-866b-d2b8cd9894bb",
    "name": "Round Utensils",
    "description": "Utensil set.",
    "hasImage": false
  },
  {
    "id": "2c250b7e-bf5a-8009-a873-de3717170e03",
    "name": "Bonsai Tree",
    "description": "Miniature Japanese tree.",
    "hasImage": false
  },
  {
    "id": "2c250b7e-bf5a-8011-91b1-efa65b8bcb6b",
    "name": "After Shave",
    "description": "Fragrance (bottle in image).",
    "hasImage": false
  },
  {
    "id": "2c250b7e-bf5a-8016-821a-c0a55e55c986",
    "name": "Nordic Ware Bakeware",
    "description": "Aluminium pans, grills, baking sheet.",
    "hasImage": false
  },
  {
    "id": "2c250b7e-bf5a-801b-8af7-cb2c8be43bac",
    "name": "Made In Brass Saucier",
    "description": "Brass saucier from Made In.",
    "hasImage": false
  },
  {
    "id": "2c250b7e-bf5a-801b-a3cc-e29781a668fb",
    "name": "KatKoot Wine",
    "description": "Bottle(s) of KatKoot wine.",
    "hasImage": false
  },
  {
    "id": "2c250b7e-bf5a-801d-aaf7-fa1ffb40c4aa",
    "name": "Borough Food Chopper",
    "description": "Manual food prep chopper.",
    "hasImage": false
  },
  {
    "id": "2c250b7e-bf5a-801e-886b-df268a419a47",
    "name": "Fjällräven Singi Seat Backpack",
    "description": "Backpack with integrated seat.",
    "hasImage": false
  },
  {
    "id": "2c250b7e-bf5a-801e-ab77-e3fc2366881f",
    "name": "Hasegawa Board & Lifter",
    "description": "Board + lifter system.",
    "hasImage": false
  },
  {
    "id": "2c250b7e-bf5a-8021-b777-e71d82b0d4c0",
    "name": "And Sons Blue Scarf",
    "description": "Blue scarf.",
    "hasImage": false
  },
  {
    "id": "2c250b7e-bf5a-8024-9314-e9fa6180b534",
    "name": "Japanese Donabe",
    "description": "Clay pot.",
    "hasImage": false
  },
  {
    "id": "2c250b7e-bf5a-802a-a9a2-eea7d0c5656f",
    "name": "Uniqlo Lambswool Sweater",
    "description": "Basic lambswool crew or v-neck from Uniqlo.",
    "hasImage": false
  },
  {
    "id": "2c250b7e-bf5a-802a-bd07-d2584b33c07c",
    "name": "Private White VC Over Jacket",
    "description": "UK-made jacket.",
    "hasImage": false
  },
  {
    "id": "2c250b7e-bf5a-802c-ae66-c72aed5d7b43",
    "name": "EMT 948 Turntable",
    "description": "Broadcast-grade vintage deck.",
    "hasImage": false
  },
  {
    "id": "2c250b7e-bf5a-8038-987b-f203da54a830",
    "name": "Vintage Champagne Sabre",
    "description": "Vintage sabre.",
    "hasImage": false
  },
  {
    "id": "2c250b7e-bf5a-8038-bf92-f1e875a02775",
    "name": "Fjällräven Singi (Pack / System)",
    "description": "Singi backpack / system (plus seat pockets already below).",
    "hasImage": false
  },
  {
    "id": "2c250b7e-bf5a-8039-970e-f807d3279e4a",
    "name": "Puebco Items (incl. Pincho)",
    "description": "Japanese industrial home goods.",
    "hasImage": false
  },
  {
    "id": "2c250b7e-bf5a-803f-acd3-f37ba9c93696",
    "name": "Snow Peak Parka",
    "description": "Technical parka from Snow Peak.",
    "hasImage": false
  },
  {
    "id": "2c250b7e-bf5a-8044-8a76-d840ba16e634",
    "name": "Hi Dock",
    "description": "Charging dock with audio.",
    "hasImage": false
  },
  {
    "id": "2c250b7e-bf5a-8047-b3f7-e51c62433792",
    "name": "Cressi / Mares Wetsuit XXL",
    "description": "Diving wetsuit XXL.",
    "hasImage": false
  },
  {
    "id": "2c250b7e-bf5a-804b-a8e2-ff7f37e9e885",
    "name": "ThruDark Centurion / Cap / Shroud",
    "description": "ThruDark outerwear & accessories.",
    "hasImage": false
  },
  {
    "id": "2c250b7e-bf5a-804e-b987-f3f367aae015",
    "name": "Sampson Morden Vintage Silver Pencil",
    "description": "Silver antique pencil.",
    "hasImage": false
  },
  {
    "id": "2c250b7e-bf5a-804f-bd90-febe724991e3",
    "name": "Paloceras Green Glasses",
    "description": "Green optical frame.",
    "hasImage": false
  },
  {
    "id": "2c250b7e-bf5a-8050-ba08-d2ffd59332c7",
    "name": "George Cox Creepers",
    "description": "",
    "hasImage": false
  },
  {
    "id": "2c250b7e-bf5a-8053-9b1c-efad1581e714",
    "name": "Heavy Vintage Chef’s Press",
    "description": "Cast-iron meat press.",
    "hasImage": false
  },
  {
    "id": "2c250b7e-bf5a-805b-ac24-f2f959263040",
    "name": "Black Gallagher Snow Peak Smock",
    "description": "Technical pullover smock.",
    "hasImage": false
  },
  {
    "id": "2c250b7e-bf5a-805d-b1bf-cc19c7ccfbe2",
    "name": "Large Bath Stool",
    "description": "A wooden stool for the shower.",
    "hasImage": false
  },
  {
    "id": "2c250b7e-bf5a-805d-b555-ffa77bfa80db",
    "name": "Sink Bracket for Stone",
    "description": "Support for stone sink.",
    "hasImage": false
  },
  {
    "id": "2c250b7e-bf5a-805e-8a77-d3343da452d6",
    "name": "Great Frog Jewellery",
    "description": "Silver rings/necklaces.",
    "hasImage": false
  },
  {
    "id": "2c250b7e-bf5a-805f-a6c0-cf314b6c2b42",
    "name": "Larger Tweezers",
    "description": "Plating tweezers.",
    "hasImage": false
  },
  {
    "id": "2c250b7e-bf5a-806a-84ca-db7dd3307523",
    "name": "Chain Mail Shoes",
    "description": "Mesh / chainmail shoes.",
    "hasImage": false
  },
  {
    "id": "2c250b7e-bf5a-806a-91ef-c8371ff16de3",
    "name": "New Oven Gloves",
    "description": "Heat-proof gloves.",
    "hasImage": false
  },
  {
    "id": "2c250b7e-bf5a-806b-87f5-cf1ba55c8d89",
    "name": "Trivet JUI",
    "description": "Heat-proof stand.",
    "hasImage": false
  },
  {
    "id": "2c250b7e-bf5a-806f-9c95-f47edfd25ed6",
    "name": "Catcher Tray (under board)",
    "description": "Tray under board for scraps.",
    "hasImage": false
  },
  {
    "id": "2c250b7e-bf5a-806f-a4aa-d93903a7d173",
    "name": "Le Chameau Black Wellies",
    "description": "High-end wellingtons.",
    "hasImage": false
  },
  {
    "id": "2c250b7e-bf5a-8070-9147-daa31ea073a5",
    "name": "Dehen Submariner Sweater Coat – Black (L)",
    "description": "Heavy knit coat, black, size L.",
    "hasImage": false
  },
  {
    "id": "2c250b7e-bf5a-8071-aa21-c2a297797aff",
    "name": "Nontron Knives",
    "description": "Classic French folding knives.",
    "hasImage": false
  },
  {
    "id": "2c250b7e-bf5a-8071-bdb2-e099e577f2c3",
    "name": "Nordic Baking Trays",
    "description": "Baking sheets / trays.",
    "hasImage": false
  },
  {
    "id": "2c250b7e-bf5a-8079-83e3-e4ddb8261d83",
    "name": "Kitchen Twine",
    "description": "Cooking string.",
    "hasImage": false
  },
  {
    "id": "2c250b7e-bf5a-807c-9179-c50a62d28be0",
    "name": "Thermapen",
    "description": "Food thermometer.",
    "hasImage": false
  },
  {
    "id": "2c250b7e-bf5a-8083-a3f7-dca9cc046d33",
    "name": "Noyer Walnut Magnetic Knife Rack",
    "description": "Walnut magnetic rack.",
    "hasImage": false
  },
  {
    "id": "2c250b7e-bf5a-8086-8056-c51578e2977e",
    "name": "Small Hasegawa Board",
    "description": "Small synthetic board.",
    "hasImage": false
  },
  {
    "id": "2c250b7e-bf5a-8086-8255-e480ba4fac9e",
    "name": "Pillows & Bedsheets",
    "description": "Bedding refresh.",
    "hasImage": false
  },
  {
    "id": "2c250b7e-bf5a-8086-989c-f2611a59cd1c",
    "name": "Foot Peels",
    "description": "Exfoliating booties.",
    "hasImage": false
  },
  {
    "id": "2c250b7e-bf5a-8086-af14-cec71eb9225e",
    "name": "Wok Tool",
    "description": "Stir-fry utensil.",
    "hasImage": false
  },
  {
    "id": "2c250b7e-bf5a-8089-8c53-cc53bf9b6644",
    "name": "Leatherman Raptor Shears",
    "description": "Foldable trauma shears.",
    "hasImage": false
  },
  {
    "id": "2c250b7e-bf5a-808e-a711-f3c9b888ffd6",
    "name": "Moscot Red-Tinted Glasses",
    "description": "Red lens variant.",
    "hasImage": false
  },
  {
    "id": "2c250b7e-bf5a-8091-b3df-c911e2e38f00",
    "name": "Business Card Holder",
    "description": "Slim card holder.",
    "hasImage": false
  },
  {
    "id": "2c250b7e-bf5a-8093-ae3e-dac11786de61",
    "name": "Japanese Potato Ricer",
    "description": "Japanese ricer / press.",
    "hasImage": false
  },
  {
    "id": "2c250b7e-bf5a-8095-97a6-fd918fee2ef6",
    "name": "Naim NAP 140 Amp",
    "description": "Classic Naim power amp.",
    "hasImage": false
  },
  {
    "id": "2c250b7e-bf5a-8095-b80c-f33e9cc00667",
    "name": "Moon Dew – Kindred Black",
    "description": "“Moon Dew” fragrance/oil from Kindred Black.",
    "hasImage": false
  },
  {
    "id": "2c250b7e-bf5a-809a-b1ea-d2cf9733b8fa",
    "name": "Vacation Candles & Sunscreen",
    "description": "Holiday kit.",
    "hasImage": false
  },
  {
    "id": "2c250b7e-bf5a-809a-b6ef-e7c9fea24ec1",
    "name": "JMM Crevel Glasses",
    "description": "Jacques Marie Mage optical frame.",
    "hasImage": false
  },
  {
    "id": "2c250b7e-bf5a-809c-b9db-dc0fc455dedb",
    "name": "RRL Jeans",
    "description": "Additional RRL denim (beyond Japanese pair already listed).",
    "hasImage": false
  },
  {
    "id": "2c250b7e-bf5a-809f-9855-ebfc3f8561ed",
    "name": "Jacques Marie Mage Zephirin 47",
    "description": "JMM Zephirin frame.",
    "hasImage": false
  },
  {
    "id": "2c250b7e-bf5a-80a0-8280-d7588bdbdcce",
    "name": "Worland JMM Sunglasses",
    "description": "Limited JMM sunglasses.",
    "hasImage": false
  },
  {
    "id": "2c250b7e-bf5a-80a2-9717-dc5e970489b5",
    "name": "Vinyl Storage Table",
    "description": "Record stand / side table.",
    "hasImage": false
  },
  {
    "id": "2c250b7e-bf5a-80a7-847b-fadbf487b317",
    "name": "Fjällräven Side Pockets",
    "description": "Singi side pockets.",
    "hasImage": false
  },
  {
    "id": "2c250b7e-bf5a-80a8-8f70-cd601b11a1f3",
    "name": "RRL Jeans (Japanese Denim)",
    "description": "Premium selvedge.",
    "hasImage": false
  },
  {
    "id": "2c250b7e-bf5a-80a8-9098-d386129d5736",
    "name": "Cutler & Gross Sunglasses",
    "description": "High-end sunglasses.",
    "hasImage": false
  },
  {
    "id": "2c250b7e-bf5a-80ae-89a4-fd1a2d75a93a",
    "name": "Fjällräven Smock",
    "description": "Field smock (likely G-1000).",
    "hasImage": false
  },
  {
    "id": "2c250b7e-bf5a-80ae-9c52-cfefaef36d8a",
    "name": "Nakiri Veg Knife",
    "description": "Japanese veg knife.",
    "hasImage": false
  },
  {
    "id": "2c250b7e-bf5a-80b1-b837-e166b36b8527",
    "name": "Gränsfors Bruks Felling Axe",
    "description": "Hand-forged axe.",
    "hasImage": false
  },
  {
    "id": "2c250b7e-bf5a-80b2-9746-cd18612a81b0",
    "name": "Round Containers",
    "description": "Storage tubs.",
    "hasImage": false
  },
  {
    "id": "2c250b7e-bf5a-80b2-b06a-d061ed52a086",
    "name": "ECWS Extreme Cold Coyote Fleece",
    "description": "Military-style ECWCS fleece.",
    "hasImage": false
  },
  {
    "id": "2c250b7e-bf5a-80b3-a228-f4456c0014f8",
    "name": "Japanese Brush",
    "description": "Traditional craft brush.",
    "hasImage": false
  },
  {
    "id": "2c250b7e-bf5a-80b4-9a8f-c65033b475e3",
    "name": "Ondine Small Saucepan",
    "description": "Small high-end saucepan from Ondine.",
    "hasImage": false
  },
  {
    "id": "2c250b7e-bf5a-80b4-b59b-e535484442c4",
    "name": "Shoe Cabinet",
    "description": "Shoe storage unit.",
    "hasImage": false
  },
  {
    "id": "2c250b7e-bf5a-80b8-b30f-e938629d7ee8",
    "name": "Green Suede Jacket",
    "description": "Vintage green suede jacket.",
    "hasImage": false
  },
  {
    "id": "2c250b7e-bf5a-80c5-b83e-c5cb74f4f924",
    "name": "Alps & Meters Ski Jumper",
    "description": "Classic ski sweater.",
    "hasImage": false
  },
  {
    "id": "2c250b7e-bf5a-80ca-b938-f28829474027",
    "name": "Japanese Fish Tank",
    "description": "Optiwhite / ADA style aquarium.",
    "hasImage": false
  },
  {
    "id": "2c250b7e-bf5a-80cc-8f67-d890afec441f",
    "name": "Uniqlo Black Trousers (take up)",
    "description": "Black Uniqlo trousers – to be hemmed / tailored.",
    "hasImage": false
  },
  {
    "id": "2c250b7e-bf5a-80cf-b77c-f06cdbc8a31e",
    "name": "Yard-O-Led Vintage Pencils",
    "description": "Regency / Deco / Corinthian.",
    "hasImage": false
  },
  {
    "id": "2c250b7e-bf5a-80d0-b8c1-f563c41ae383",
    "name": "Vintage Sake Warmer",
    "description": "Ceramic warmer.",
    "hasImage": false
  },
  {
    "id": "2c250b7e-bf5a-80d1-b604-d348581cc7ab",
    "name": "Speed Rail Shelf Bolt-On",
    "description": "Rail under shelf / board.",
    "hasImage": false
  },
  {
    "id": "2c250b7e-bf5a-80da-87fe-df0158440d17",
    "name": "Leatherman Signal Multi-Tool",
    "description": "19-in-1 outdoor multi-tool.",
    "hasImage": false
  },
  {
    "id": "2c250b7e-bf5a-80dc-810b-f3c1eb350d2c",
    "name": "Apple Wallet",
    "description": "MagSafe leather wallet.",
    "hasImage": false
  },
  {
    "id": "2c250b7e-bf5a-80dc-9056-f5661b862b6c",
    "name": "Meater 2 Thermometer",
    "description": "Wireless meat probe.",
    "hasImage": false
  },
  {
    "id": "2c250b7e-bf5a-80df-929f-e3e169f1ab12",
    "name": "Japanese Mis-en-Place Set",
    "description": "Prep trays/utensils, J-style.",
    "hasImage": false
  },
  {
    "id": "2c250b7e-bf5a-80e4-8144-ee5670cf939a",
    "name": "Porch Brush (general)",
    "description": "Good porch / yard brush.",
    "hasImage": false
  },
  {
    "id": "2c250b7e-bf5a-80e4-bb4e-f32cd5d4998c",
    "name": "M&S Beckham Shawl Collar Cardigan",
    "description": "M&S x Beckham shawl knit.",
    "hasImage": false
  },
  {
    "id": "2c250b7e-bf5a-80e5-bc2d-ee630b5154e3",
    "name": "Boning Knife + Tutorial",
    "description": "Boning knife + chicken butchery TikTok tutorial.",
    "hasImage": false
  },
  {
    "id": "2c250b7e-bf5a-80e8-9a63-ce90e87c8def",
    "name": "Oceanic Housing",
    "description": "Underwater camera housing.",
    "hasImage": false
  },
  {
    "id": "2c250b7e-bf5a-80e8-af84-dd49af798fc3",
    "name": "German Slicer Knife",
    "description": "Slicing knife (Wüsthof style).",
    "hasImage": false
  },
  {
    "id": "2c250b7e-bf5a-80ea-8591-e6d21bbbc835",
    "name": "Otherwise Shirts",
    "description": "Minimalist shirts.",
    "hasImage": false
  },
  {
    "id": "2c250b7e-bf5a-80ec-b0c8-fd077779882a",
    "name": "Oyster Tempo Cooler",
    "description": "Premium insulated cooler.",
    "hasImage": false
  },
  {
    "id": "2c250b7e-bf5a-80ee-bca3-fd3f2f339951",
    "name": "Vendome Black Acetate JMM",
    "description": "Black acetate JMM frame.",
    "hasImage": false
  },
  {
    "id": "2c250b7e-bf5a-80ef-b377-d507c907f7e4",
    "name": "0.5cm Cube Skewers",
    "description": "Japanese skewers.",
    "hasImage": false
  },
  {
    "id": "2c250b7e-bf5a-80fc-90c3-c15ec6e941eb",
    "name": "Clutch Culture Shirt",
    "description": "Graphic / streetwear shirt.",
    "hasImage": false
  },
  {
    "id": "2c250b7e-bf5a-80fe-b938-cb72a32f4550",
    "name": "Door Mat",
    "description": "New doormat.",
    "hasImage": false
  },
  {
    "id": "2c250b7e-bf5a-80ff-b1b8-fc6f13cf47cb",
    "name": "Resting Rack",
    "description": "Cooling / resting rack.",
    "hasImage": false
  }
]
